Workbook
Name Slicer_Department1: #N/A

Sheet employee_data
A1: Index | B1: Employee_ID | C1: Age | D1: Department | E1: Is_Manager | F1: Join_Date | G1: Experience | H1: Salary
A2: 0 | B2: 8794 | C2: 60 | D2: Finance | E2: FALSE | F2: 34417 | G2: 30 | H2: 238668
A3: 1 | B3: 8222 | C3: 28 | D3: Sales | E3: TRUE | F3: 29197 | G3: 13 | H3: 105995
A4: 2 | B4: 7643 | C4: 30 | D4: Marketing | E4: FALSE | F4: 36063 | G4: 11 | H4: 96120
A5: 3 | B5: 2737 | C5: 38 | D5: HR | E5: TRUE | F5: 40870 | G5: 20 | H5: 153525
A6: 4 | B6: 8557 | C6: 61 | D6: HR | E6: TRUE | F6: 28041 | G6: 31 | H6: 249192
A7: 5 | B7: 8484 | C7: 31 | D7: Marketing | E7: FALSE | F7: 30109 | G7: 14 | H7: 112443
A8: 6 | B8: 5854 | C8: 64 | D8: Finance | E8: FALSE | F8: 29902 | G8: 33 | H8: 269150
A9: 7 | B9: 6012 | C9: 33 | D9: Finance | E9: FALSE | F9: 30587 | G9: 13 | H9: 99541
A10: 8 | B10: 7462 | C10: 34 | D10: Finance | E10: FALSE | F10: 44218 | G10: 15 | H10: 119128
A11: 9 | B11: 7276 | C11: 23 | D11: Finance | E11: FALSE | F11: 41915 | G11: 11 | H11: 83249
A12: 10 | B12: 6621 | C12: 51 | D12: IT | E12: TRUE | F12: 27100 | G12: 26 | H12: 201259
A13: 11 | B13: 7461 | C13: 43 | D13: IT | E13: TRUE | F13: 33397 | G13: 17 | H13: 144477
... A501: 499 | B501: 7744 | C501: 29 | D501: Finance | E501: TRUE | F501: 32315 | G501: 15 | H501: 114758

Sheet New data
A1: Index | B1: Employee_ID | C1: Age | D1: Age group | E1: Department | F1: Is_Manager | G1: Join_Date | H1: Experience | I1: Experience group | J1: Salary | K1: Salary group
A2: 0 | B2: 8794 | C2: 60 | D2: {=_xlfn.IFS(C2<30, "20-29",C2<40, "30-39",C2<50, "40-49",C2<60, "50-59",Table4[[#This Row],[Age]]>=60, "60+" )} -> 60+ | E2: Finance | F2: FALSE | G2: 34417 | H2: 30 | I2: {=_xlfn.IFS(Table4[[#This Row],[Experience]]<15, "7-15 YEARS",Table4[[#This Row],[Experience]]<23, "15-23 YEARS",Table4[[#This Row],[Experience]]<30, "23-30 YEARS",Table4[[#This Row],[Experience]]>=30, "30+ YEARS")} -> 30+ YEARS | J2: 238668 | K2: {=_xlfn.IFS(Table4[[#This Row],[Salary]]<50000, "0-50K",Table4[[#This Row],[Salary]]<100000, "50K-1L",Table4[[#This Row],[Salary]]<150000, "1L-1.5L",Table4[[#This Row],[Salary]]<200000, "1.5-2L",Table4[[#This Row],[Salary]]>=200000, "2L+")} -> 2L+
A3: 1 | B3: 8222 | C3: 28 | D3: {=_xlfn.IFS(C3<30, "20-29",C3<40, "30-39",C3<50, "40-49",C3<60, "50-59",Table4[[#This Row],[Age]]>=60, "60+" )} -> 20-29 | E3: Sales | F3: TRUE | G3: 29197 | H3: 13 | I3: {=_xlfn.IFS(Table4[[#This Row],[Experience]]<15, "7-15 YEARS",Table4[[#This Row],[Experience]]<23, "15-23 YEARS",Table4[[#This Row],[Experience]]<30, "23-30 YEARS",Table4[[#This Row],[Experience]]>=30, "30+ YEARS")} -> 7-15 YEARS | J3: 105995 | K3: {=_xlfn.IFS(Table4[[#This Row],[Salary]]<50000, "0-50K",Table4[[#This Row],[Salary]]<100000, "50K-1L",Table4[[#This Row],[Salary]]<150000, "1L-1.5L",Table4[[#This Row],[Salary]]<200000, "1.5-2L",Table4[[#This Row],[Salary]]>=200000, "2L+")} -> 1L-1.5L
A4: 2 | B4: 7643 | C4: 30 | D4: {=_xlfn.IFS(C4<30, "20-29",C4<40, "30-39",C4<50, "40-49",C4<60, "50-59",Table4[[#This Row],[Age]]>=60, "60+" )} -> 30-39 | E4: Marketing | F4: FALSE | G4: 36063 | H4: 11 | I4: {=_xlfn.IFS(Table4[[#This Row],[Experience]]<15, "7-15 YEARS",Table4[[#This Row],[Experience]]<23, "15-23 YEARS",Table4[[#This Row],[Experience]]<30, "23-30 YEARS",Table4[[#This Row],[Experience]]>=30, "30+ YEARS")} -> 7-15 YEARS | J4: 96120 | K4: {=_xlfn.IFS(Table4[[#This Row],[Salary]]<50000, "0-50K",Table4[[#This Row],[Salary]]<100000, "50K-1L",Table4[[#This Row],[Salary]]<150000, "1L-1.5L",Table4[[#This Row],[Salary]]<200000, "1.5-2L",Table4[[#This Row],[Salary]]>=200000, "2L+")} -> 50K-1L
A5: 3 | B5: 2737 | C5: 38 | D5: {=_xlfn.IFS(C5<30, "20-29",C5<40, "30-39",C5<50, "40-49",C5<60, "50-59",Table4[[#This Row],[Age]]>=60, "60+" )} -> 30-39 | E5: HR | F5: TRUE | G5: 40870 | H5: 20 | I5: {=_xlfn.IFS(Table4[[#This Row],[Experience]]<15, "7-15 YEARS",Table4[[#This Row],[Experience]]<23, "15-23 YEARS",Table4[[#This Row],[Experience]]<30, "23-30 YEARS",Table4[[#This Row],[Experience]]>=30, "30+ YEARS")} -> 15-23 YEARS | J5: 153525 | K5: {=_xlfn.IFS(Table4[[#This Row],[Salary]]<50000, "0-50K",Table4[[#This Row],[Salary]]<100000, "50K-1L",Table4[[#This Row],[Salary]]<150000, "1L-1.5L",Table4[[#This Row],[Salary]]<200000, "1.5-2L",Table4[[#This Row],[Salary]]>=200000, "2L+")} -> 1.5-2L
A6: 4 | B6: 8557 | C6: 61 | D6: {=_xlfn.IFS(C6<30, "20-29",C6<40, "30-39",C6<50, "40-49",C6<60, "50-59",Table4[[#This Row],[Age]]>=60, "60+" )} -> 60+ | E6: HR | F6: TRUE | G6: 28041 | H6: 31 | I6: {=_xlfn.IFS(Table4[[#This Row],[Experience]]<15, "7-15 YEARS",Table4[[#This Row],[Experience]]<23, "15-23 YEARS",Table4[[#This Row],[Experience]]<30, "23-30 YEARS",Table4[[#This Row],[Experience]]>=30, "30+ YEARS")} -> 30+ YEARS | J6: 249192 | K6: {=_xlfn.IFS(Table4[[#This Row],[Salary]]<50000, "0-50K",Table4[[#This Row],[Salary]]<100000, "50K-1L",Table4[[#This Row],[Salary]]<150000, "1L-1.5L",Table4[[#This Row],[Salary]]<200000, "1.5-2L",Table4[[#This Row],[Salary]]>=200000, "2L+")} -> 2L+
A7: 5 | B7: 8484 | C7: 31 | D7: {=_xlfn.IFS(C7<30, "20-29",C7<40, "30-39",C7<50, "40-49",C7<60, "50-59",Table4[[#This Row],[Age]]>=60, "60+" )} -> 30-39 | E7: Marketing | F7: FALSE | G7: 30109 | H7: 14 | I7: {=_xlfn.IFS(Table4[[#This Row],[Experience]]<15, "7-15 YEARS",Table4[[#This Row],[Experience]]<23, "15-23 YEARS",Table4[[#This Row],[Experience]]<30, "23-30 YEARS",Table4[[#This Row],[Experience]]>=30, "30+ YEARS")} -> 7-15 YEARS | J7: 112443 | K7: {=_xlfn.IFS(Table4[[#This Row],[Salary]]<50000, "0-50K",Table4[[#This Row],[Salary]]<100000, "50K-1L",Table4[[#This Row],[Salary]]<150000, "1L-1.5L",Table4[[#This Row],[Salary]]<200000, "1.5-2L",Table4[[#This Row],[Salary]]>=200000, "2L+")} -> 1L-1.5L
A8: 6 | B8: 5854 | C8: 64 | D8: {=_xlfn.IFS(C8<30, "20-29",C8<40, "30-39",C8<50, "40-49",C8<60, "50-59",Table4[[#This Row],[Age]]>=60, "60+" )} -> 60+ | E8: Finance | F8: FALSE | G8: 29902 | H8: 33 | I8: {=_xlfn.IFS(Table4[[#This Row],[Experience]]<15, "7-15 YEARS",Table4[[#This Row],[Experience]]<23, "15-23 YEARS",Table4[[#This Row],[Experience]]<30, "23-30 YEARS",Table4[[#This Row],[Experience]]>=30, "30+ YEARS")} -> 30+ YEARS | J8: 269150 | K8: {=_xlfn.IFS(Table4[[#This Row],[Salary]]<50000, "0-50K",Table4[[#This Row],[Salary]]<100000, "50K-1L",Table4[[#This Row],[Salary]]<150000, "1L-1.5L",Table4[[#This Row],[Salary]]<200000, "1.5-2L",Table4[[#This Row],[Salary]]>=200000, "2L+")} -> 2L+
A9: 7 | B9: 6012 | C9: 33 | D9: {=_xlfn.IFS(C9<30, "20-29",C9<40, "30-39",C9<50, "40-49",C9<60, "50-59",Table4[[#This Row],[Age]]>=60, "60+" )} -> 30-39 | E9: Finance | F9: FALSE | G9: 30587 | H9: 13 | I9: {=_xlfn.IFS(Table4[[#This Row],[Experience]]<15, "7-15 YEARS",Table4[[#This Row],[Experience]]<23, "15-23 YEARS",Table4[[#This Row],[Experience]]<30, "23-30 YEARS",Table4[[#This Row],[Experience]]>=30, "30+ YEARS")} -> 7-15 YEARS | J9: 99541 | K9: {=_xlfn.IFS(Table4[[#This Row],[Salary]]<50000, "0-50K",Table4[[#This Row],[Salary]]<100000, "50K-1L",Table4[[#This Row],[Salary]]<150000, "1L-1.5L",Table4[[#This Row],[Salary]]<200000, "1.5-2L",Table4[[#This Row],[Salary]]>=200000, "2L+")} -> 50K-1L
A10: 8 | B10: 7462 | C10: 34 | D10: {=_xlfn.IFS(C10<30, "20-29",C10<40, "30-39",C10<50, "40-49",C10<60, "50-59",Table4[[#This Row],[Age]]>=60, "60+" )} -> 30-39 | E10: Finance | F10: FALSE | G10: 44218 | H10: 15 | I10: {=_xlfn.IFS(Table4[[#This Row],[Experience]]<15, "7-15 YEARS",Table4[[#This Row],[Experience]]<23, "15-23 YEARS",Table4[[#This Row],[Experience]]<30, "23-30 YEARS",Table4[[#This Row],[Experience]]>=30, "30+ YEARS")} -> 15-23 YEARS | J10: 119128 | K10: {=_xlfn.IFS(Table4[[#This Row],[Salary]]<50000, "0-50K",Table4[[#This Row],[Salary]]<100000, "50K-1L",Table4[[#This Row],[Salary]]<150000, "1L-1.5L",Table4[[#This Row],[Salary]]<200000, "1.5-2L",Table4[[#This Row],[Salary]]>=200000, "2L+")} -> 1L-1.5L
A11: 9 | B11: 7276 | C11: 23 | D11: {=_xlfn.IFS(C11<30, "20-29",C11<40, "30-39",C11<50, "40-49",C11<60, "50-59",Table4[[#This Row],[Age]]>=60, "60+" )} -> 20-29 | E11: Finance | F11: FALSE | G11: 41915 | H11: 11 | I11: {=_xlfn.IFS(Table4[[#This Row],[Experience]]<15, "7-15 YEARS",Table4[[#This Row],[Experience]]<23, "15-23 YEARS",Table4[[#This Row],[Experience]]<30, "23-30 YEARS",Table4[[#This Row],[Experience]]>=30, "30+ YEARS")} -> 7-15 YEARS | J11: 83249 | K11: {=_xlfn.IFS(Table4[[#This Row],[Salary]]<50000, "0-50K",Table4[[#This Row],[Salary]]<100000, "50K-1L",Table4[[#This Row],[Salary]]<150000, "1L-1.5L",Table4[[#This Row],[Salary]]<200000, "1.5-2L",Table4[[#This Row],[Salary]]>=200000, "2L+")} -> 50K-1L
A12: 10 | B12: 6621 | C12: 51 | D12: {=_xlfn.IFS(C12<30, "20-29",C12<40, "30-39",C12<50, "40-49",C12<60, "50-59",Table4[[#This Row],[Age]]>=60, "60+" )} -> 50-59 | E12: IT | F12: TRUE | G12: 27100 | H12: 26 | I12: {=_xlfn.IFS(Table4[[#This Row],[Experience]]<15, "7-15 YEARS",Table4[[#This Row],[Experience]]<23, "15-23 YEARS",Table4[[#This Row],[Experience]]<30, "23-30 YEARS",Table4[[#This Row],[Experience]]>=30, "30+ YEARS")} -> 23-30 YEARS | J12: 201259 | K12: {=_xlfn.IFS(Table4[[#This Row],[Salary]]<50000, "0-50K",Table4[[#This Row],[Salary]]<100000, "50K-1L",Table4[[#This Row],[Salary]]<150000, "1L-1.5L",Table4[[#This Row],[Salary]]<200000, "1.5-2L",Table4[[#This Row],[Salary]]>=200000, "2L+")} -> 2L+
A13: 11 | B13: 7461 | C13: 43 | D13: {=_xlfn.IFS(C13<30, "20-29",C13<40, "30-39",C13<50, "40-49",C13<60, "50-59",Table4[[#This Row],[Age]]>=60, "60+" )} -> 40-49 | E13: IT | F13: TRUE | G13: 33397 | H13: 17 | I13: {=_xlfn.IFS(Table4[[#This Row],[Experience]]<15, "7-15 YEARS",Table4[[#This Row],[Experience]]<23, "15-23 YEARS",Table4[[#This Row],[Experience]]<30, "23-30 YEARS",Table4[[#This Row],[Experience]]>=30, "30+ YEARS")} -> 15-23 YEARS | J13: 144477 | K13: {=_xlfn.IFS(Table4[[#This Row],[Salary]]<50000, "0-50K",Table4[[#This Row],[Salary]]<100000, "50K-1L",Table4[[#This Row],[Salary]]<150000, "1L-1.5L",Table4[[#This Row],[Salary]]<200000, "1.5-2L",Table4[[#This Row],[Salary]]>=200000, "2L+")} -> 1L-1.5L
... A501: 499 | B501: 7744 | C501: 29 | D501: {=_xlfn.IFS(C501<30, "20-29",C501<40, "30-39",C501<50, "40-49",C501<60, "50-59",Table4[[#This Row],[Age]]>=60, "60+" )} -> 20-29 | E501: Finance | F501: TRUE | G501: 32315 | H501: 15 | I501: {=_xlfn.IFS(Table4[[#This Row],[Experience]]<15, "7-15 YEARS",Table4[[#This Row],[Experience]]<23, "15-23 YEARS",Table4[[#This Row],[Experience]]<30, "23-30 YEARS",Table4[[#This Row],[Experience]]>=30, "30+ YEARS")} -> 15-23 YEARS | J501: 114758 | K501: {=_xlfn.IFS(Table4[[#This Row],[Salary]]<50000, "0-50K",Table4[[#This Row],[Salary]]<100000, "50K-1L",Table4[[#This Row],[Salary]]<150000, "1L-1.5L",Table4[[#This Row],[Salary]]<200000, "1.5-2L",Table4[[#This Row],[Salary]]>=200000, "2L+")} -> 1L-1.5L

Sheet Dashboard
A1: DASHBOARD

Sheet CALCULATIONS
C2: ANALYSIS USING EXCEL FUNCTIONS | M2: RECOMMENDATION
A4: 1) WHAT IS THE TOTAL NUMBER OF EMPLOYEES? | F4: =COUNT(Table4[Employee_ID]) -> 500 | M4: 1. Marketing ₹1,77,127 Highest, Sales ₹1,64,615 Lowest
G5: FINANCE | H5: MARKETING | I5: SALES | J5: HR | K5: IT | M5: Sales brings revenue but lowest paid. Give them more bonus.
A6: 2) HOW MANY EMPLOYEES WORK IN EACH DEPARTMENT? | G6: =COUNTIF(Table4[Department],'New data'!E499) -> 102 | H6: =COUNTIF(Table4[Department],'New data'!E492) -> 95 | I6: =COUNTIF(Table4[Department],'New data'!E481) -> 106 | J6: =COUNTIF(Table4[Department],'New data'!E487) -> 87 | K6: =COUNTIF(Table4[Department],'New data'!E483) -> 110 | M6: 2. Sales = 60 Managers (Highest) Too many managers in Sales. Reduce managers, save cost.
A7: 3) HOW MANY MANAGERS ARE THERE IN EACH DEPARTMENT? | G7: =COUNTIFS(Table4[Is_Manager],'New data'!F481,Table4[Department],'New data'!E501) -> 45 | H7: =COUNTIFS(Table4[Is_Manager],'New data'!F481,Table4[Department],'New data'!E482) -> 47 | I7: =COUNTIFS(Table4[Department],'New data'!E481,Table4[Is_Manager],'New data'!F481) -> 60 | J7: =COUNTIFS(Table4[Is_Manager],'New data'!F481,Table4[Department],'New data'!E475) -> 46 | K7: =COUNTIFS(Table4[Is_Manager],'New data'!F479,Table4[Department],'New data'!E480) -> 59 | M7: 3. Hiring Trend Fluctuating Hiring is random. Make fixed yearly hiring plan.
M8: 5. Age 40-49 = 170 Max, 20-29 = 77 Min
A9: 5) WHAT IS THE AVERAGE EXPERIENCE OF ALL EMPLOYEES? | G9: =AVERAGE(Table4[Experience]) -> 21.316 | M9: Workforce is old. Hire freshers urgently otherwise retirement problem.
A10: 6) WHAT IS THE AVERAGE SALARY OF MANAGERS VS NON-MANAGERS? | G10: =AVERAGEIF(Table4[Is_Manager],'New data'!F479,Table4[Salary]) -> 171841.04 | I10: =AVERAGEIF(Table4[Is_Manager],'New data'!F475,Table4[Salary]) -> 169358.19 | M10: 7. Manager vs Non-Manager Gap only ₹2,482Gap too less. No benefit to become manager. Give managers 10% extra. | N10: .
B12: DASHBOARD RECOMMENDED CHART
A13: 1) HIGHEST AVG SALARY BY DEPT | K13: ANALYSIS USING DASHBOARD | N13: INSIGHTS
A14: 2) MANAGER VS NON MANAGER BY DEPT | J14: Which department has the highest number of employees? | N14: IT has the largest workforce with 110 employees (22% of total), indicating IT is the core department.
A15: 3) AVG SALARY - MANAGER VS NON MAN | J15: Which department has the lowest number of employees? | N15: The HR department has the smallest workforce with 87 employees (17.4% of total).
A16: 4) YEAR VS HIRE TREND | J16: Whar percentage of the total workforce does the largest | N16: The largest department (IT) represents approximately 22% of the total 500 employees.
A17: 5) SALARY DISTRIBUTION | J17: department represent?
A18: 6) AGE GROUP DISTRIBUTION | J18: Which department has the highest average salary? | N18: Marketing has the highest average salary among the departments, indicating high value for marketing roles.
A19: 7) EMPLOYEE DISTRIBUTION BY EXP & DEPT | J19: Which departments have salaries below overall company average? | N19: HR and Finance have salaries below the overall company average of ₹1,70,634.
J20: Which department has the highest number of managers? | N20: Sales has the highest number of managers with 60 managers, suggesting strong leadership structure.
J21: Are departments with more employees necessarily having more managers? | N21: No. IT has the largest workforce (110) but Sales (106) has more managers (60 vs 59).
J22: Is there a significant salary gap between managers and non-managers? | N22: No. Manager avg is ₹1,71,841 vs Non-Manager ₹1,69,358. Gap is only 1.4%, showing fair pay policy.
J23: Is there any noticeable yearly hiring pattern? | N23: The hiring trend shows a noticeable increase in employee joining during 2018-2020, indicating expansion phase.
J24: Which age group has the highest number of employees? | N24: The 50+ age group has the highest concentration, indicating a mature and experienced workforce.
J25: Which salary range has the most employees? | N25: The ₹1.5L - ₹2L salary range has the most employees, which matches the company average of ₹1.70L.
J26: How is experience distributed across departments? | N26: Finance and IT have more senior employees (21+ years), while HR has relatively more junior employees.

Sheet EDA
J1: EDA - EMPLOYEE DATA
C2: OBJECTIVE | M2: DATASET OVERVIEW
B3: • Analyze 500 employee records to understand department | K3: Total employees | N3: 500
B4: distribution and salary trends | K4: Departments | N4: 5
B5: • Support data driven decision making for workforce management | K5: Time period | N5: 1970 - 2025
K6: Total columns | N6: 11 (Dept, salary, experience, age, hire year etc..)
C7: DATA CLEANING
B8: • Checked for missing values: No missing values found | L8: HEADCOUNT BY DEPARTMENT
B9: • Checked for duplicates: No duplicate Employee IDs | L9: DEPARTMENT | N9: EMPLOYEES | P9: SHARE(%)
L10: Finance | N10: 102 | P10: 0.204
C11: AVERAGE SALARY BY ROLES | L11: HR | N11: 87 | P11: 0.174
B12: ROLE TYPE | D12: STATUS | F12: AVG SALARY | L12: IT | N12: 110 | P12: 0.22
B13: MANAGER | D13: 257 | F13: 171841 | L13: Marketing | N13: 95 | P13: 0.19
B14: NON - MANAGER | D14: 243 | F14: 169358 | L14: Sales | N14: 106 | P14: 0.212
L15: TOTAL | N15: 500 | P15: 1

Sheet HIGHEST AVG SALARY BY DEPT
A3: Row Labels | B3: Average of Salary
A4: Finance | B4: 167374.46
A5: HR | B5: 172150.57
A6: IT | B6: 172650.85
A7: Marketing | B7: 177127.2
A8: Sales | B8: 164615.22
A9: Grand Total | B9: 170634.37

Sheet MANAGER VS NON MANAGER BY DEPT
A3: Count of Employee_ID | B3: Column Labels
A4: Row Labels | B4: FALSE | C4: TRUE | D4: Grand Total
A5: Finance | B5: 57 | C5: 45 | D5: 102
A6: HR | B6: 41 | C6: 46 | D6: 87
A7: IT | B7: 51 | C7: 59 | D7: 110
A8: Marketing | B8: 48 | C8: 47 | D8: 95
A9: Sales | B9: 46 | C9: 60 | D9: 106
A10: Grand Total | B10: 243 | C10: 257 | D10: 500

Sheet AVG SALARY - MANAGER VS NON MAN
A3: Row Labels | B3: Average of Salary
A4: FALSE | B4: 169358.19
A5: TRUE | B5: 171841.04
A6: Grand Total | B6: 170634.37

Sheet YEAR VS HIRE TREND
A3: Row Labels | B3: Count of Employee_ID
A4: 1970 | B4: 8
A5: 1971 | B5: 7
A6: 1972 | B6: 9
A7: 1973 | B7: 12
A8: 1974 | B8: 12
A9: 1975 | B9: 8
A10: 1976 | B10: 14
A11: 1977 | B11: 5
A12: 1978 | B12: 8
A13: 1979 | B13: 8
A14: 1980 | B14: 9
A15: 1981 | B15: 11
... A60: Grand Total | B60: 500

Sheet SALARY DISTRIBUTION
A3: Row Labels | B3: Count of Employee_ID
A4: 0-50K | B4: 1
A5: 50K-1L | B5: 47
A6: 1L-1.5L | B6: 130
A7: 1.5-2L | B7: 167
A8: 2L+ | B8: 155
A9: Grand Total | B9: 500

Sheet AGE GROUP DISTRIBUTION
A3: Row Labels | B3: Count of Employee_ID
A4: 20-29 | B4: 77
A5: 30-39 | B5: 106
A6: 40-49 | B6: 147
A7: 50+ | B7: 170
A8: Grand Total | B8: 500

Sheet EMPLOYEE DSTRBTION BY EXP&DEPT 
A3: Count of Employee_ID | B3: Column Labels
A4: Row Labels | B4: 7-15 YEARS | C4: 15-23 YEARS | D4: 23-30 YEARS | E4: 30+ YEARS | F4: Grand Total
A5: Finance | B5: 14 | C5: 48 | D5: 34 | E5: 6 | F5: 102
A6: HR | B6: 15 | C6: 32 | D6: 31 | E6: 9 | F6: 87
A7: IT | B7: 21 | C7: 33 | D7: 40 | E7: 16 | F7: 110
A8: Marketing | B8: 15 | C8: 38 | D8: 26 | E8: 16 | F8: 95
A9: Sales | B9: 22 | C9: 40 | D9: 39 | E9: 5 | F9: 106
A10: Grand Total | B10: 87 | C10: 191 | D10: 170 | E10: 52 | F10: 500
